tsmorph/__init__.py
tsmorph/tsmorph.py
tsmorph/utils.py
tsmorph-0.1.1.dist-info/LICENSE.txt
tsmorph-0.1.1.dist-info/METADATA
tsmorph-0.1.1.dist-info/WHEEL
tsmorph-0.1.1.dist-info/top_level.txt
tsmorph-0.1.1.dist-info/RECORD
