Metadata-Version: 2.2
Name: tsmorph
Version: 0.1.1
Summary: A package for generating semi-synthetic time series using morphing techniques.
Home-page: https://github.com/yourusername/tsmorph
Author: Moisés Santos
License: GPL-3.0-only
Requires-Python: >=3.7
License-File: LICENSE.txt
Requires-Dist: numpy
Requires-Dist: pandas
Requires-Dist: matplotlib
Requires-Dist: pycatch22
Requires-Dist: neuralforecast
Dynamic: home-page
Dynamic: requires-python
